mashyperscaler_aws/__init__.py
mashyperscaler_aws/check_ec2_instances.py
mashyperscaler_aws-0.1.4.dist-info/METADATA
mashyperscaler_aws-0.1.4.dist-info/WHEEL
mashyperscaler_aws-0.1.4.dist-info/top_level.txt
mashyperscaler_aws-0.1.4.dist-info/RECORD
