Metadata-Version: 2.1
Name: mashyperscaler-aws
Version: 0.1.4
Summary: EC2 Instance Counter
Author: Amit M Mangalvedkar
License: MIT
